pyproject.toml
setup.py
OpenHomeLab/__init__.py
OpenHomeLab/main.py
OpenHomeLab/tree.py
OpenHomeLab.egg-info/PKG-INFO
OpenHomeLab.egg-info/SOURCES.txt
OpenHomeLab.egg-info/dependency_links.txt
OpenHomeLab.egg-info/entry_points.txt
OpenHomeLab.egg-info/requires.txt
OpenHomeLab.egg-info/top_level.txt